pmatlib/__init__.py
pmatlib-0.1.0.dist-info/licenses/LICENSE
pmatlib-0.1.0.dist-info/METADATA
pmatlib-0.1.0.dist-info/WHEEL
pmatlib-0.1.0.dist-info/top_level.txt
pmatlib-0.1.0.dist-info/RECORD
