Metadata-Version: 2.4
Name: pmatlib
Version: 0.1.0
Summary: A lightweight library for Progressive Moving Average Transform (PMAT) on signals.
Author-email: Rabah Mokhtari <rabah.mokhtari@univ-msila.dz>
License: MIT License
Project-URL: Homepage, https://github.com/mokhtarirabah/pmatlib
Keywords: pmat,signal-processing,moving-average,time-series,feature-extraction,cnn,ecg,fault-diagnosis,peak-detection
Classifier: Programming Language :: Python :: 3
Classifier: License :: OSI Approved :: MIT License
Classifier: Operating System :: OS Independent
Requires-Python: >=3.7
License-File: LICENSE
Requires-Dist: numpy
Dynamic: license-file
